assignment_1/Registers.v
module Registers
(
    rst_i,
    clk_i,
    RS1addr_i,
    RS2addr_i,
    RDaddr_i, 
    RDdata_i,
    RegWrite_i, 
    RS1data_o, 
    RS2data_o 
);

// Ports
input               rst_i;
input               clk_i;
input   [4:0]       RS1addr_i;
input   [4:0]       RS2addr_i;
input   [4:0]       RDaddr_i;
input   [31:0]      RDdata_i;
input               RegWrite_i;
output  signed [31:0]      RS1data_o; 
output  signed [31:0]      RS2data_o;
integer i;

// Register File
reg signed [31:0]      register        [0:31];

// Read Data      
assign  RS1data_o = register[RS1addr_i];
assign  RS2data_o = register[RS2addr_i];

// Write Data   
always@(posedge clk_i or negedge rst_i) begin
    if (~rst_i) begin
        for (i=0; i<32; i++) begin
            register[i] <= 32'b0;
        end
    end
    else if(RegWrite_i && RDaddr_i != 5'b0) begin
        register[RDaddr_i] <= RDdata_i;
    end
end

endmodule

SH'scourse/assignment_1/Registers_tb.v
`timescale 1ns / 1ps

module Registers_tb;

    // Inputs
    reg rst_i;
    reg clk_i;
    reg [4:0] RS1addr_i;
    reg [4:0] RS2addr_i;
    reg [4:0] RDaddr_i;
    reg [31:0] RDdata_i;
    reg RegWrite_i;

    // Outputs
    wire signed [31:0] RS1data_o;
    wire signed [31:0] RS2data_o;

    // Instantiate the Registers module
    Registers uut (
        .rst_i(rst_i),
        .clk_i(clk_i),
        .RS1addr_i(RS1addr_i),
        .RS2addr_i(RS2addr_i),
        .RDaddr_i(RDaddr_i),
        .RDdata_i(RDdata_i),
        .RegWrite_i(RegWrite_i),
        .RS1data_o(RS1data_o),
        .RS2data_o(RS2data_o)
    );

    // Clock generation
    initial clk_i = 0;
    always #5 clk_i = ~clk_i; // 10ns clock period

    // Testbench procedure
    initial begin
        $dumpfile("Registers_test.vcd"); // 指定波形檔案名稱
        $dumpvars(0, Registers_tb); // 記錄所有信號變化
        $display("Starting Registers Testbench...");
        
        // Reset the registers
        rst_i = 0;
        RegWrite_i = 0;
        RDaddr_i = 5'b0;
        RDdata_i = 32'b0;
        #10; // Wait for reset
        
        rst_i = 1; // Release reset
        #10;

        // Test 1: Write to a register and read it back
        RDaddr_i = 5'd1; // Write to register 1
        RDdata_i = 32'hDEADBEEF;
        RegWrite_i = 1;
        #10;

        RS1addr_i = 5'd1; // Read register 1
        RegWrite_i = 0;
        #10;
        $display("Test 1: Write/Read register 1. RS1data_o = %h (Expected: DEADBEEF)", RS1data_o);

        // Test 2: Write to multiple registers
        RDaddr_i = 5'd2;
        RDdata_i = 32'h12345678;
        RegWrite_i = 1;
        #10;

        RDaddr_i = 5'd3;
        RDdata_i = 32'hABCDEF01;
        #10;

        RS1addr_i = 5'd2;
        RS2addr_i = 5'd3;
        RegWrite_i = 0;
        #10;
        $display("Test 2: RS1data_o = %h (Expected: 12345678), RS2data_o = %h (Expected: ABCDEF01)", RS1data_o, RS2data_o);

        // Test 3: Write to register 0 (should not change)
        RDaddr_i = 5'b0; // Attempt to write to register 0
        RDdata_i = 32'hFFFFFFFF;
        RegWrite_i = 1;
        #10;

        RS1addr_i = 5'b0; // Read register 0
        RegWrite_i = 0;
        #10;
        $display("Test 3: Write/Read register 0. RS1data_o = %h (Expected: 00000000)", RS1data_o);

        // Test 4: Reset and verify all registers are cleared
        rst_i = 0; // Assert reset
        #10;
        rst_i = 1; // Release reset
        #10;

        RS1addr_i = 5'd1;
        RS2addr_i = 5'd2;
        #10;
        $display("Test 4: After reset, RS1data_o = %h (Expected: 00000000), RS2data_o = %h (Expected: 00000000)", RS1data_o, RS2data_o);

        $display("Registers Testbench Completed.");
        $stop;
    end

endmodule

assignment_1/Registers_test.vcd
$date
	Mon Nov 18 11:27:51 2024
$end
$version
	Icarus Verilog
$end
$timescale
	1ps
$end
$scope module Registers_tb $end
$var wire 32 ! RS2data_o [31:0] $end
$var wire 32 " RS1data_o [31:0] $end
$var reg 5 # RDaddr_i [4:0] $end
$var reg 32 $ RDdata_i [31:0] $end
$var reg 5 % RS1addr_i [4:0] $end
$var reg 5 & RS2addr_i [4:0] $end
$var reg 1 ' RegWrite_i $end
$var reg 1 ( clk_i $end
$var reg 1 ) rst_i $end
$scope module uut $end
$var wire 5 * RDaddr_i [4:0] $end
$var wire 32 + RDdata_i [31:0] $end
$var wire 5 , RS1addr_i [4:0] $end
$var wire 32 - RS1data_o [31:0] $end
$var wire 5 . RS2addr_i [4:0] $end
$var wire 32 / RS2data_o [31:0] $end
$var wire 1 ' RegWrite_i $end
$var wire 1 ( clk_i $end
$var wire 1 ) rst_i $end
$var integer 32 0 i [31:0] $end
$upscope $end
$upscope $end
$enddefinitions $end
#0
$dumpvars
b100000 0
bx /
bx .
bx -
bx ,
b0 +
b0 *
0)
0(
0'
bx &
bx %
b0 $
b0 #
bx "
bx !
$end
#5000
b100000 0
1(
#10000
0(
1)
#15000
1(
#20000
0(
1'
b11011110101011011011111011101111 $
b11011110101011011011111011101111 +
b1 #
b1 *
#25000
1(
#30000
0(
0'
b11011110101011011011111011101111 "
b11011110101011011011111011101111 -
b1 %
b1 ,
#35000
1(
#40000
0(
1'
b10010001101000101011001111000 $
b10010001101000101011001111000 +
b10 #
b10 *
#45000
1(
#50000
0(
b10101011110011011110111100000001 $
b10101011110011011110111100000001 +
b11 #
b11 *
#55000
1(
#60000
0(
0'
b10101011110011011110111100000001 !
b10101011110011011110111100000001 /
b11 &
b11 .
b10010001101000101011001111000 "
b10010001101000101011001111000 -
b10 %
b10 ,
#65000
1(
#70000
0(
1'
b11111111111111111111111111111111 $
b11111111111111111111111111111111 +
b0 #
b0 *
#75000
1(
#80000
0(
0'
b0 "
b0 -
b0 %
b0 ,
#85000
1(
#90000
b0 !
b0 /
b100000 0
0(
0)
#95000
b100000 0
1(
#100000
0(
1)
#105000
1(
#110000
0(
b10 &
b10 .
b1 %
b1 ,
