assignment_1/ALU.v
module ALU(
    input signed [31:0] data1_i,
    input signed [31:0] data2_i,
    input [2:0] ALUCtrl_i,
    output  reg signed [31 : 0] data_o,
	output          zero_o
);

assign zero_o = (data_o == 0)? 1'b1 : 1'b0;

always @(data1_i or data2_i or ALUCtrl_i) begin
    case(ALUCtrl_i)
        3'b000: data_o = $signed(data1_i + data2_i); // Addition
        3'b001: data_o = $signed(data1_i - data2_i); // Subtraction
        3'b010: data_o = $signed(data1_i & data2_i); // Bitwise AND
        3'b011: data_o = $signed(data1_i | data2_i); // Bitwise OR
        3'b100: data_o = $signed(data1_i ^ data2_i); // Bitwise XOR
        3'b101: data_o = $signed(data1_i << data2_i); // Left Shift 
        3'b110: data_o = $signed(data1_i >>> data2_i[4:0]); // Arithmetic Right Shift  
        3'b111: data_o = $signed(data1_i >> data2_i); // Logical Right Shift

        default: data_o = 0; // Default value
    endcase
end

endmodule

SH'scourse/assignment_2/ALU_tb.v
`timescale 1ns / 1ps

module ALU_tb;

    // Inputs
    reg signed [31:0] data1_i;
    reg signed [31:0] data2_i;
    reg [2:0] ALUCtrl_i;

    // Outputs
    wire signed [31:0] data_o;
    wire zero_o;

    // Instantiate the ALU module
    ALU uut (
        .data1_i(data1_i),
        .data2_i(data2_i),
        .ALUCtrl_i(ALUCtrl_i),
        .data_o(data_o),
        .zero_o(zero_o)
    );

    // Testbench procedure
    initial begin
        $dumpfile("ALU_test.vcd"); // 指定波形檔案名稱
        $dumpvars(0, ALU_tb); // 記錄所有信號變化

        // Test Addition
        data1_i = 32'hFFFFFFFF; // 2^32-1
        data2_i = 32'h00000001; // 1
        ALUCtrl_i = 3'b000; // Addition
        #10;
        $display("Addition: %d + %d = %d, Zero: %b", data1_i, data2_i, data_o, zero_o);

        // Test Subtraction
        data1_i = 32'h00000000; // 32
        data2_i = 32'h00000001; // 32
        ALUCtrl_i = 3'b001; // Subtraction
        #10;
        $display("Subtraction: %d - %d = %d, Zero: %b", data1_i, data2_i, data_o, zero_o);

        // Test Bitwise AND
        data1_i = 32'h000000FF;
        data2_i = 32'h0000000F;
        ALUCtrl_i = 3'b010; // AND
        #10;
        $display("AND: %h & %h = %h, Zero: %b", data1_i, data2_i, data_o, zero_o);

        // Test Bitwise OR
        data1_i = 32'h000000F0;
        data2_i = 32'h0000000F;
        ALUCtrl_i = 3'b011; // OR
        #10;
        $display("OR: %h | %h = %h, Zero: %b", data1_i, data2_i, data_o, zero_o);

        // Test Bitwise XOR
        data1_i = 32'h000000F0;
        data2_i = 32'h0000000F;
        ALUCtrl_i = 3'b100; // XOR
        #10;
        $display("XOR: %h ^ %h = %h, Zero: %b", data1_i, data2_i, data_o, zero_o);

        // Test Left Shift
        data1_i = 32'h00000001;
        data2_i = 32'h00000002; // Shift by 2
        ALUCtrl_i = 3'b101; // Left Shift
        #10;
        $display("Left Shift: %h << %d = %h, Zero: %b", data1_i, data2_i, data_o, zero_o);

        // Test Arithmetic Right Shift
        data1_i = 32'hFFFFFFF0; // -16 in 2's complement
        data2_i = 32'h00000002; // Shift by 2
        ALUCtrl_i = 3'b110; // Arithmetic Right Shift
        #10;
        $display("Arithmetic Right Shift: %h >>> %d = %h, Zero: %b", data1_i, data2_i, data_o, zero_o);

        // Test Logical Right Shift
        data1_i = 32'hFFFFFFF0; // -16 in 2's complement
        data2_i = 32'h00000002; // Shift by 2
        ALUCtrl_i = 3'b111; // Logical Right Shift
        #10;
        $display("Logical Right Shift: %h >> %d = %h, Zero: %b", data1_i, data2_i, data_o, zero_o);

        // Default case
        data1_i = 32'h00000010;
        data2_i = 32'h00000010;
        ALUCtrl_i = 3'bxxx; // Invalid operation
        #10;
        $display("Default case: %h, Zero: %b", data_o, zero_o);

        $stop;
    end

endmodule

SH'scourse/assignment_1/ALU_test.vcd
$date
	Fri Nov 22 19:14:05 2024
$end
$version
	Icarus Verilog
$end
$timescale
	1ps
$end
$scope module ALU_tb $end
$var wire 1 ! zero_o $end
$var wire 32 " data_o [31:0] $end
$var reg 3 # ALUCtrl_i [2:0] $end
$var reg 32 $ data1_i [31:0] $end
$var reg 32 % data2_i [31:0] $end
$scope module uut $end
$var wire 3 & ALUCtrl_i [2:0] $end
$var wire 32 ' data1_i [31:0] $end
$var wire 32 ( data2_i [31:0] $end
$var wire 1 ! zero_o $end
$var reg 32 ) data_o [31:0] $end
$upscope $end
$upscope $end
$enddefinitions $end
#0
$dumpvars
b0 )
b1 (
b11111111111111111111111111111111 '
b0 &
b1 %
b11111111111111111111111111111111 $
b0 #
b0 "
1!
$end
#10000
0!
b11111111111111111111111111111111 "
b11111111111111111111111111111111 )
b1 #
b1 &
b0 $
b0 '
#20000
b1111 "
b1111 )
b10 #
b10 &
b1111 %
b1111 (
b11111111 $
b11111111 '
#30000
b11111111 "
b11111111 )
b11 #
b11 &
b11110000 $
b11110000 '
#40000
b100 #
b100 &
#50000
b100 "
b100 )
b101 #
b101 &
b10 %
b10 (
b1 $
b1 '
#60000
b11111111111111111111111111111100 "
b11111111111111111111111111111100 )
b110 #
b110 &
b11111111111111111111111111110000 $
b11111111111111111111111111110000 '
#70000
b111111111111111111111111111100 "
b111111111111111111111111111100 )
b111 #
b111 &
#80000
1!
b0 "
b0 )
bx #
bx &
b10000 %
b10000 (
b10000 $
b10000 '
